{"id":"113121092","name":"Brandt Vernon","email":"brandt.m.vernon-1@ou.edu","certifications":[{"certName":"Yellow","expiration":"09-17-2018","isShopCert":true}],"notes":"","signedWaiver":"Yes","timesVisited":"15","strikes":"0","timeStampHistory":[{"start":"01-30-2018 05:48 PM","end":"01-30-2018 07:29 PM"},{"start":"01-31-2018 10:58 AM","end":"01-31-2018 12:08 PM"},{"start":"01-31-2018 04:24 PM","end":"01-31-2018 05:55 PM"},{"start":"01-31-2018 07:36 PM","end":"01-31-2018 08:44 PM"},{"start":"02-01-2018 05:13 PM","end":"02-01-2018 05:57 PM"},{"start":"02-02-2018 05:11 PM","end":"02-02-2018 08:56 PM"},{"start":"02-03-2018 11:48 AM","end":"02-03-2018 01:47 PM"},{"start":"02-05-2018 03:24 PM","end":"02-05-2018 08:13 PM"},{"start":"02-07-2018 08:11 PM","end":"02-07-2018 08:45 PM"},{"start":"02-09-2018 06:53 PM","end":"02-09-2018 09:28 PM"},{"start":"02-16-2018 12:20 PM","end":"02-16-2018 01:49 PM"},{"start":"02-16-2018 02:38 PM","end":"02-16-2018 06:41 PM"},{"start":"02-16-2018 06:53 PM","end":"02-16-2018 08:55 PM"},{"start":"02-26-2018 04:28 PM","end":"02-26-2018 04:43 PM"},{"start":"02-26-2018 04:49 PM","end":"02-26-2018 08:19 PM"}]}